firs/__init__.py
firs/configuration.py
firs/simple_test.py
firs/replicator/AbstractReplicator.py
firs/replicator/Reformulations.py
firs/replicator/__init__.py
firs/replicator/Shuttering/Shuttering.py
firs/replicator/Shuttering/__init__.py
firs/replicator/Shuttering/_check_inputs.py
firs/replicator/Shuttering/_even_sharding.py
firs/replicator/Shuttering/_get_shuttering_id.py
firs/replicator/Shuttering/_import_precomputed_shards.py
firs/replicator/Shuttering/_random_sharding.py
firs/replicator/Shuttering/build_shards.py
firs/replicator/Shuttering/evaluate.py
firs/replicator/Shuttering/get_replicates.py
firs/replicator/Shuttering/shuttering_utils.py
firs/retrieval/__init__.py
firs/retrieval/indexing.py
firs/retrieval/pipeline_factory.py
firs/retrieval/pyterrier2trec.py
firs/retrieval/retrieving.py
firs/trecdata/__init__.py
firs/trecdata/TrecCollection/TrecCollection.py
firs/trecdata/TrecCollection/__init__.py
firs/trecdata/TrecCollection/evaluate.py
firs/trecdata/TrecCollection/get_topics.py
firs/trecdata/TrecCollection/import_collection.py
firs/trecdata/TrecCollection/misc.py
firs/trecdata/TrecCollection/parallel_evaluate.py
firs/trecdata/TrecCollection/topic_parsers/__init__.py
firs/trecdata/TrecCollection/topic_parsers/pandas_csv_reader.py
firs/utils/Logger.py
firs/utils/__init__.py
firs/utils/utils.py
firs-0.0.9.dist-info/LICENCE
firs-0.0.9.dist-info/METADATA
firs-0.0.9.dist-info/WHEEL
firs-0.0.9.dist-info/top_level.txt
firs-0.0.9.dist-info/RECORD
