Metadata-Version: 2.1
Name: firs
Version: 0.0.9
Summary: firs: a Framework for Information Retrieval Systems
Home-page: https://github.com/guglielmof/firs
Author: Guglielmo Faggioli
Author-email: guglielmo.faggioli@phd.unipd.it
License: UNKNOWN
Project-URL: Bug Tracker, https://github.com/pypa/sampleproject/issues
Platform: UNKNOWN
Classifier: Programming Language :: Python :: 3
Classifier: License :: OSI Approved :: MIT License
Classifier: Operating System :: OS Independent
Requires-Python: >=3.8
License-File: LICENCE
